Leer_PDDDF/Funciones.py
Leer_PDDDF/__init__.py
Leer_PDFdavid-0.0.1.dist-info/METADATA
Leer_PDFdavid-0.0.1.dist-info/WHEEL
Leer_PDFdavid-0.0.1.dist-info/top_level.txt
Leer_PDFdavid-0.0.1.dist-info/RECORD
