Metadata-Version: 2.1
Name: Leer_PDFdavid
Version: 0.0.1
Summary: Librería para leer ficheros PDFs y extraer la información en formato str
Home-page: https://github.com/afernandez119
Author: Antonio Fernandez Troyano
Author-email: a.fernandez.troyano@gmail.com
License: MIT
Requires-Dist: pymupdf
